sylloge/__init__.py
sylloge/base.py
sylloge/create_statistic.py
sylloge/dask_utils.py
sylloge/id_mapped.py
sylloge/med_bbk_loader.py
sylloge/moviegraph_benchmark_loader.py
sylloge/my_typing.py
sylloge/oaei_loader.py
sylloge/open_ea_loader.py
sylloge/utils.py
sylloge-0.3.0.dist-info/LICENSE
sylloge-0.3.0.dist-info/WHEEL
sylloge-0.3.0.dist-info/METADATA
sylloge-0.3.0.dist-info/RECORD
