Metadata-Version: 2.1
Name: sylloge
Version: 0.3.0
Summary: Small library to simplify collecting and loading of entity alignment benchmark datasets
Home-page: https://github.com/dobraczka/sylloge
License: MIT
Keywords: entity resolution,knowledge graph,datasets,entity alignment
Author: Daniel Obraczka
Author-email: obraczka@informatik.uni-leipzig.de
Requires-Python: >=3.8,<4.0
Classifier: Development Status :: 4 - Beta
Classifier: License :: OSI Approved :: MIT License
Classifier: Programming Language :: Python
Classifier: Programming Language :: Python :: 3
Classifier: Programming Language :: Python :: 3.8
Classifier: Programming Language :: Python :: 3.9
Classifier: Programming Language :: Python :: 3.10
Classifier: Programming Language :: Python :: 3.11
Classifier: Programming Language :: Python :: 3 :: Only
Classifier: Programming Language :: Python :: 3.10
Classifier: Programming Language :: Python :: 3.8
Classifier: Programming Language :: Python :: 3.9
Provides-Extra: docs
Requires-Dist: Sphinx (>=5.0.0,<6.0.0) ; extra == "docs"
Requires-Dist: dask (>=2022.01.0)
Requires-Dist: eche (>=0.2.1,<0.3.0)
Requires-Dist: insegel (>=1.3.1,<2.0.0) ; extra == "docs"
Requires-Dist: moviegraphbenchmark (>=1.1.0,<2.0.0)
Requires-Dist: pandas (>=1.0)
Requires-Dist: pyarrow
Requires-Dist: pystow (>=0.4.6,<0.5.0)
Requires-Dist: python-slugify (>=7.0.0)
Requires-Dist: sphinx-autodoc-typehints (>=1.19.2,<2.0.0) ; extra == "docs"
Requires-Dist: sphinx-automodapi (>=0.14.1,<0.15.0) ; extra == "docs"
Project-URL: Bug Tracker, https://github.com/dobraczka/sylloge/issues
Project-URL: Documentation, https://sylloge.readthedocs.io
Project-URL: Repository, https://github.com/dobraczka/sylloge
Project-URL: Source, https://github.com/dobraczka/sylloge
